aeroot/__init__.py
aeroot/aeroot.py
aeroot/avd.py
aeroot/cli.py
aeroot/emulator.py
aeroot/gdb.py
aeroot/util.py
config/kernel/3.10.0+_i686.yaml
config/kernel/3.18.56+_i686.yaml
config/kernel/3.18.91+_i686.yaml
config/kernel/4.14.112+_i686.yaml
config/kernel/4.14.112+_x86_64.yaml
config/kernel/4.4.124+_i686.yaml
config/kernel/4.4.124+_x86_64.yaml
config/kernel/5.10.102-android13-0-00549-g255b30f804ac-ab8238117_i686.yaml
config/kernel/5.10.102-android13-0-00549-g255b30f804ac-ab8238117_x86_64.yaml
config/kernel/5.10.107-android13-2-00451-g7ba447d0399b-ab8409457_x86_64.yaml
config/kernel/5.10.15-android12-0-01814-gfca78df78ef2-ab7137072_x86_64.yaml
config/kernel/5.10.21-android12-0-01012-gcc574f0d3698-ab7214561_x86_64.yaml
config/kernel/5.10.21-android12-0-01145-ge82381ad9a3f-ab7230153_x86_64.yaml
config/kernel/5.10.35-android12-4-00865-gd9d0c09e0a3b-ab7349034_x86_64.yaml
config/kernel/5.10.4-android12-0-03442-gf2684370d34d-ab7068937_x86_64.yaml
config/kernel/5.10.43-android12-6-00231-g54e7412d4ff9-ab7460289_x86_64.yaml
config/kernel/5.10.43-android12-9-00001-ga30f38980440-ab7882141_x86_64.yaml
config/kernel/5.10.66-android12-9-00022-g2d6a43c0364d-ab7992900_i686.yaml
config/kernel/5.10.66-android12-9-00041-gfa9c9074531e-ab7914766_x86_64.yaml
config/kernel/5.15.32-android13-3-00067-g7b5e736d7c63-ab8474665_x86_64.yaml
config/kernel/5.15.41-android13-6-02245-g158384f20d1e-ab8610100_x86_64.yaml
config/kernel/5.15.41-android13-8-00055-g4f5025129fe8-ab8949913_x86_64.yaml
config/kernel/5.15.41-android13-8-00205-gf1bf82c3dacd-ab8747247_x86_64.yaml
config/kernel/5.15.83-android14-5-00138-g5e28b848962c-ab9412825_x86_64.yaml
config/kernel/5.4.36-00815-g3b29042c17b1_i686.yaml
config/kernel/5.4.36-00815-g3b29042c17b1_x86_64.yaml
config/kernel/5.4.43-00621-g90087296b3b1_i686.yaml
config/kernel/5.4.43-00621-g90087296b3b1_x86_64.yaml
config/kernel/5.4.47-01061-g22e35a1de440_i686.yaml
config/kernel/5.4.47-01061-g22e35a1de440_x86_64.yaml
aeroot-0.3.9.dist-info/LICENSE.txt
aeroot-0.3.9.dist-info/METADATA
aeroot-0.3.9.dist-info/WHEEL
aeroot-0.3.9.dist-info/entry_points.txt
aeroot-0.3.9.dist-info/top_level.txt
aeroot-0.3.9.dist-info/RECORD
