Metadata-Version: 2.1
Name: aeroot
Version: 0.3.9
Summary: Android Emulator Rooting system
Home-page: https://github.com/quarkslab/AERoot
Author: Eric Le Guevel (ha0)
Author-email: eleguevel@quarkslab.com
License: Apache License 2.0
Classifier: Development Status :: 3 - Alpha
Classifier: Topic :: Security
Classifier: Topic :: Utilities
License-File: LICENSE.txt
Requires-Dist: pure-python-adb
Requires-Dist: pygdbmi (>=0.9.0.3)
Requires-Dist: colorama
Requires-Dist: pyyaml
